swagger_dialect/__init__.py
swagger_dialect/error.py
swagger_dialect/swagger_dbapi.py
swagger_dialect/swagger_dialect.py
swagger_dialect-0.0.3.dist-info/LICENSE
swagger_dialect-0.0.3.dist-info/METADATA
swagger_dialect-0.0.3.dist-info/WHEEL
swagger_dialect-0.0.3.dist-info/top_level.txt
swagger_dialect-0.0.3.dist-info/RECORD
