Metadata-Version: 2.1
Name: swagger-dialect
Version: 0.0.3
Summary: Swagger definition SQLAlchemy reflection
Home-page: https://github.com/robertbetts/swagger-dialect
Author: robertbetts
License: UNKNOWN
Keywords: import,physical address,file path
Platform: UNKNOWN
Classifier: Development Status :: 3 - Alpha
Classifier: Intended Audience :: Developers
Classifier: License :: OSI Approved :: MIT License
Classifier: Operating System :: OS Independent
Classifier: Programming Language :: Python
Classifier: Programming Language :: Python :: 3
Classifier: Programming Language :: Python :: 3.10
Classifier: Programming Language :: Python :: Implementation :: CPython
Classifier: Programming Language :: Python :: Implementation :: PyPy
Classifier: Topic :: Database :: Front-Ends
Requires-Python: >3.10.0
License-File: LICENSE
Requires-Dist: sqlalchemy (>=1.4.0)
Requires-Dist: pyyaml (>=6.0)
Provides-Extra: docs
Provides-Extra: testing
Requires-Dist: pytest (>=7.0.0) ; extra == 'testing'
Requires-Dist: sqlacodegen (>=3.0rc1) ; extra == 'testing'
